nats_nsc-0.4.1.dist-info/METADATA
nats_nsc-0.4.1.dist-info/WHEEL
nats_nsc-0.4.1.dist-info/licenses/LICENSE
nats_nsc/__init__.py
nats_nsc/create_user.py
nats_nsc-0.4.1.dist-info/RECORD
