Metadata-Version: 2.1
Name: nats-nsc
Version: 0.4.1
Summary: Limited python nsc utility equivalent, for user creation and signing JWTs.
Author-Email: Mikołaj Nowak <12396461+m3nowak@users.noreply.github.com>
License: MIT
Requires-Python: >=3.8
Requires-Dist: pyJWT~=2.6.0
Requires-Dist: aiofiles~=23.1.0
Requires-Dist: nkeys~=0.1.0
